README.md
setup.py
./mobio/__init__.py
./mobio/sdks/__init__.py
./mobio/sdks/base/__init__.py
./mobio/sdks/base/apis/__init__.py
./mobio/sdks/base/apis/check_service.py
./mobio/sdks/base/common/__init__.py
./mobio/sdks/base/common/lang_config.py
./mobio/sdks/base/common/mobio_exception.py
./mobio/sdks/base/common/system_config.py
./mobio/sdks/base/common/utils.py
./mobio/sdks/base/configs/__init__.py
./mobio/sdks/base/controllers/__init__.py
./mobio_base_sdk.egg-info/PKG-INFO
./mobio_base_sdk.egg-info/SOURCES.txt
./mobio_base_sdk.egg-info/dependency_links.txt
./mobio_base_sdk.egg-info/requires.txt
./mobio_base_sdk.egg-info/top_level.txt