Metadata-Version: 2.1
Name: mobio-base-sdk
Version: 1.0.14
Summary: Mobio project SDK
Home-page: 
Author: MOBIO
Author-email: contact@mobio.vn
License: MIT
Requires-Python: >=3.7
